compressgpt/__init__.py
compressgpt/compute_metrics.py
compressgpt/config.py
compressgpt/create_dataset.py
compressgpt/label_space.py
compressgpt/model_check.py
compressgpt/model_runner.py
compressgpt/trainer.py
compressgpt/utils.py
compressgpt_core-0.1.5.dist-info/licenses/LICENSE
compressgpt_core-0.1.5.dist-info/METADATA
compressgpt_core-0.1.5.dist-info/WHEEL
compressgpt_core-0.1.5.dist-info/top_level.txt
compressgpt_core-0.1.5.dist-info/RECORD
