Metadata-Version: 2.4
Name: compressgpt-core
Version: 0.1.5
Summary: LLM Compression and Optimization Library - Build the smallest runnable models that preserve target accuracy
Author: chandan678
License: MIT
Project-URL: Homepage, https://github.com/chandan678/compressgpt
Project-URL: Repository, https://github.com/chandan678/compressgpt
Project-URL: Issues, https://github.com/chandan678/compressgpt/issues
Keywords: llm,compression,optimization,fine-tuning,machine-learning,deep-learning,transformers,sft,supervised-fine-tuning
Classifier: Development Status :: 3 - Alpha
Classifier: Intended Audience :: Developers
Classifier: Intended Audience :: Science/Research
Classifier: License :: OSI Approved :: MIT License
Classifier: Operating System :: OS Independent
Classifier: Programming Language :: Python :: 3
Classifier: Programming Language :: Python :: 3.9
Classifier: Programming Language :: Python :: 3.10
Classifier: Programming Language :: Python :: 3.11
Classifier: Programming Language :: Python :: 3.12
Classifier: Topic :: Scientific/Engineering :: Artificial Intelligence
Requires-Python: >=3.9
License-File: LICENSE
Requires-Dist: pandas>=1.5.0
Requires-Dist: datasets>=2.0.0
Requires-Dist: transformers>=4.40.0
Requires-Dist: scikit-learn>=1.0.0
Requires-Dist: torch>=2.0.0
Requires-Dist: tqdm>=4.60.0
Requires-Dist: numpy>=1.20.0
Requires-Dist: peft>=0.10.0
Requires-Dist: trl==0.19.0
Requires-Dist: accelerate>=0.20.0
Requires-Dist: bitsandbytes>=0.41.0
Requires-Dist: llama-cpp-python>=0.2.0
Provides-Extra: dev
Requires-Dist: pytest>=7.0.0; extra == "dev"
Requires-Dist: pytest-cov>=4.0.0; extra == "dev"
Dynamic: license-file
